MANIFEST.in
README.rst
setup.py
src/sentry_pivotal/__init__.py
src/sentry_pivotal/models.py
src/sentry_pivotal/plugin.py
src/sentry_pivotal.egg-info/PKG-INFO
src/sentry_pivotal.egg-info/SOURCES.txt
src/sentry_pivotal.egg-info/dependency_links.txt
src/sentry_pivotal.egg-info/entry_points.txt
src/sentry_pivotal.egg-info/not-zip-safe
src/sentry_pivotal.egg-info/requires.txt
src/sentry_pivotal.egg-info/top_level.txt