Metadata-Version: 1.0
Name: sentry-pivotal
Version: 0.1.0
Summary: A Sentry extension which integrates with Pivotal Tracker.
Home-page: http://github.com/getsentry/sentry-pivotal
Author: David Cramer
Author-email: dcramer@gmail.com
License: BSD
Platform: UNKNOWN
Classifier: Framework :: Django
Classifier: Intended Audience :: Developers
Classifier: Intended Audience :: System Administrators
Classifier: Operating System :: OS Independent
Classifier: Topic :: Software Development
